{"kind": "youtube#playlistListResponse", "etag": "7Q6zZ-bXKcuPGcKMiym655vKOyw", "nextPageToken": "CAUQAA", "pageInfo": {"totalResults": 108, "resultsPerPage": 5}, "items": [{"kind": "youtube#playlist", "etag": "WPHVa0Ycpbv74BFyFVisL2skF0Q", "id": "PLxn-kpJHbPx2xsLWXrRuZLFc9RxLhP42s"}, {"kind": "youtube#playlist", "etag": "0MmWm41y69B_YWInQMzrLyHrqA0", "id": "PLxn-kpJHbPx0UJceDNIMUAcjYGYFnW8yo"}, {"kind": "youtube#playlist", "etag": "5vG4A1SxiYDNp3fIr4r31Ehz4BY", "id": "PLxn-kpJHbPx24wpNu7OLKDo5hj6-fJUme"}, {"kind": "youtube#playlist", "etag": "EMT7k-lw96NzXxabidsOTHfL1yA", "id": "PLxn-kpJHbPx2MdNmghnw2yJBKzaMRLAHh"}, {"kind": "youtube#playlist", "etag": "ZSsqU28YuX_VdMNV89IKkvyhsVQ", "id": "PLxn-kpJHbPx1kM3Bhv9ohR1qglGdwarFu"}]}